Workbook

Sheet Financial Data
A1: Month | B1: Quarter | C1: Revenue | D1: Marketing | E1: Payroll | F1: Rent | G1: Other Costs | H1: Total Expenses | I1: Profit | J1: Profit Margin
A2: =DATE(2025,1,1) -> 45658 | B2: ="Q"&ROUNDUP(MONTH(A2)/3,0) -> Q1 | C2: 125000 | D2: 6250 | E2: 42000 | F2: 12000 | G2: 22500 | H2: =SUM(D2:G2) -> 82750 | I2: =C2-H2 -> 42250 | J2: =I2/C2 -> 0.338
A3: =EDATE(A2,1) -> 45689 | B3: ="Q"&ROUNDUP(MONTH(A3)/3,0) -> Q1 | C3: 130000 | D3: 13750 | E3: 42000 | F3: 12000 | G3: 18200 | H3: =SUM(D3:G3) -> 85950 | I3: =C3-H3 -> 44050 | J3: =I3/C3 -> 0.33884615
A4: =EDATE(A3,1) -> 45717 | B4: ="Q"&ROUNDUP(MONTH(A4)/3,0) -> Q1 | C4: 137800 | D4: 13750 | E4: 42000 | F4: 12000 | G4: 19536 | H4: =SUM(D4:G4) -> 87286 | I4: =C4-H4 -> 50514 | J4: =I4/C4 -> 0.36657475
A5: =EDATE(A4,1) -> 45748 | B5: ="Q"&ROUNDUP(MONTH(A5)/3,0) -> Q2 | C5: 133666 | D5: 12125 | E5: 42000 | F5: 12000 | G5: 20049.9 | H5: =SUM(D5:G5) -> 86174.9 | I5: =C5-H5 -> 47491.1 | J5: =I5/C5 -> 0.35529678
A6: =EDATE(A5,1) -> 45778 | B6: ="Q"&ROUNDUP(MONTH(A6)/3,0) -> Q2 | C6: 137675.98 | D6: 9506 | E6: 42000 | F6: 12000 | G6: 16521.118 | H6: =SUM(D6:G6) -> 80027.118 | I6: =C6-H6 -> 57648.862 | J6: =I6/C6 -> 0.41872854
A7: =EDATE(A6,1) -> 45809 | B7: ="Q"&ROUNDUP(MONTH(A7)/3,0) -> Q2 | C7: 139052.74 | D7: 11549.79 | E7: 42000 | F7: 12000 | G7: 22248.438 | H7: =SUM(D7:G7) -> 87798.228 | I7: =C7-H7 -> 51254.511 | J7: =I7/C7 -> 0.36859764
A8: =EDATE(A7,1) -> 45839 | B8: ="Q"&ROUNDUP(MONTH(A8)/3,0) -> Q3 | C8: 134881.16 | D8: 14539.902 | E8: 47500 | F8: 12000 | G8: 16185.739 | H8: =SUM(D8:G8) -> 90225.641 | I8: =C8-H8 -> 44655.516 | J8: =I8/C8 -> 0.33107305
A9: =EDATE(A8,1) -> 45870 | B9: ="Q"&ROUNDUP(MONTH(A9)/3,0) -> Q3 | C9: 142974.03 | D9: 17950.17 | E9: 47500 | F9: 12000 | G9: 24305.585 | H9: =SUM(D9:G9) -> 101755.75 | I9: =C9-H9 -> 41218.272 | J9: =I9/C9 -> 0.28829203
A10: =EDATE(A9,1) -> 45901 | B10: ="Q"&ROUNDUP(MONTH(A10)/3,0) -> Q3 | C10: 138684.81 | D10: 19616.972 | E10: 47500 | F10: 12000 | G10: 22189.569 | H10: =SUM(D10:G10) -> 101306.54 | I10: =C10-H10 -> 37378.265 | J10: =I10/C10 -> 0.26951954
A11: =EDATE(A10,1) -> 45931 | B11: ="Q"&ROUNDUP(MONTH(A11)/3,0) -> Q4 | C11: 148392.74 | D11: 13954.206 | E11: 47500 | F11: 12000 | G11: 21807.129 | H11: =SUM(D11:G11) -> 95261.335 | I11: =C11-H11 -> 53131.408 | J11: =I11/C11 -> 0.35804586
A12: =EDATE(A11,1) -> 45962 | B12: ="Q"&ROUNDUP(MONTH(A12)/3,0) -> Q4 | C12: 160264.16 | D12: 10452.969 | E12: 47500 | F12: 12000 | G12: 20834.341 | H12: =SUM(D12:G12) -> 90787.31 | I12: =C12-H12 -> 69476.852 | J12: =I12/C12 -> 0.43351459
A13: =EDATE(A12,1) -> 45992 | B13: ="Q"&ROUNDUP(MONTH(A13)/3,0) -> Q4 | C13: 155456.24 | D13: 12229.974 | E13: 47500 | F13: 12000 | G13: 27982.123 | H13: =SUM(D13:G13) -> 99712.096 | I13: =C13-H13 -> 55744.141 | J13: =I13/C13 -> 0.35858414

Sheet Dashboard
T1: Month | U1: Sum of Profit Margin | W1: Month | X1: Sum of Revenue | Y1: Sum of Profit | AA1: Expense Type | AB1: Amount
E2: Total Revenue | F2: =SUM('Financial Data'!C2:C13) -> 1683847.9 | T2: 45658 | U2: 0.338 | W2: 45658 | X2: 125000 | Y2: 42250 | AA2: Marketing | AB2: =SUM('Financial Data'!D2:D13) -> 155674.98
E3: Total Profit | F3: =SUM('Financial Data'!I2:I13) -> 594812.93 | T3: 45689 | U3: 0.33884615 | W3: 45689 | X3: 130000 | Y3: 44050 | AA3: Payroll | AB3: =SUM('Financial Data'!E2:E13) -> 537000
E4: Avg Profit Margin | F4: =AVERAGE('Financial Data'!J2:J13) -> 0.35208942 | T4: 45717 | U4: 0.36657475 | W4: 45717 | X4: 137800 | Y4: 50514 | AA4: Rent | AB4: =SUM('Financial Data'!F2:F13) -> 144000
T5: 45748 | U5: 0.35529678 | W5: 45748 | X5: 133666 | Y5: 47491.1 | AA5: Other Costs | AB5: =SUM('Financial Data'!G2:G13) -> 252359.94
T6: 45778 | U6: 0.41872854 | W6: 45778 | X6: 137675.98 | Y6: 57648.862
T7: 45809 | U7: 0.36859764 | W7: 45809 | X7: 139052.74 | Y7: 51254.511
T8: 45839 | U8: 0.33107305 | W8: 45839 | X8: 134881.16 | Y8: 44655.516
T9: 45870 | U9: 0.28829203 | W9: 45870 | X9: 142974.03 | Y9: 41218.272
T10: 45901 | U10: 0.26951954 | W10: 45901 | X10: 138684.81 | Y10: 37378.265
T11: 45931 | U11: 0.35804586 | W11: 45931 | X11: 148392.74 | Y11: 53131.408
T12: 45962 | U12: 0.43351459 | W12: 45962 | X12: 160264.16 | Y12: 69476.852
T13: 45992 | U13: 0.35858414 | W13: 45992 | X13: 155456.24 | Y13: 55744.141
T14: Grand Total | U14: 4.2250731 | W14: Grand Total | X14: 1683847.9 | Y14: 594812.93
